Workbook

Sheet Start here
A1: Construction Kit – CIS deductions tracker + reverse charge invoice
A2: A record-keeping aid, not tax advice. Check gov.uk/what-is-the-construction-industry-scheme and HMRC's VAT reverse charge guidance.
A4: For contractors (you pay subcontractors)
A5: 1. Subcontractors: add each one with their verification status: Gross (0%), Registered (20%) or Unregistered (30%).
A6: 2. Payments: one row per payment. Split labour from materials; deduction is worked out on labour only.
A7: 3. Monthly return: totals per tax month (6th to 5th). Return due by the 19th, payment by the 22nd (electronic).
A8: 4. Statement: give each subcontractor a statement within 14 days of the end of the tax month.
A10: For subcontractors (deductions taken from you)
A11: 5. Deductions suffered: log what contractors deducted; claim it against your tax bill in Self Assessment (or via your company's payroll).
A13: Reverse charge (VAT-registered subcontractors)
A14: 6. DRC invoice: for CIS services to a VAT- and CIS-registered customer who isn't the end user, don't charge VAT; the customer accounts for it.

Sheet Subcontractors
A1: Name | B1: UTR | C1: Verification number | D1: Status | E1: Rate
E2: =IF(D2="Gross",0,IF(D2="Registered",0.2,IF(D2="Unregistered",0.3,"")))
E3: =IF(D3="Gross",0,IF(D3="Registered",0.2,IF(D3="Unregistered",0.3,"")))
E4: =IF(D4="Gross",0,IF(D4="Registered",0.2,IF(D4="Unregistered",0.3,"")))
E5: =IF(D5="Gross",0,IF(D5="Registered",0.2,IF(D5="Unregistered",0.3,"")))
E6: =IF(D6="Gross",0,IF(D6="Registered",0.2,IF(D6="Unregistered",0.3,"")))
E7: =IF(D7="Gross",0,IF(D7="Registered",0.2,IF(D7="Unregistered",0.3,"")))
E8: =IF(D8="Gross",0,IF(D8="Registered",0.2,IF(D8="Unregistered",0.3,"")))
E9: =IF(D9="Gross",0,IF(D9="Registered",0.2,IF(D9="Unregistered",0.3,"")))
E10: =IF(D10="Gross",0,IF(D10="Registered",0.2,IF(D10="Unregistered",0.3,"")))
E11: =IF(D11="Gross",0,IF(D11="Registered",0.2,IF(D11="Unregistered",0.3,"")))
E12: =IF(D12="Gross",0,IF(D12="Registered",0.2,IF(D12="Unregistered",0.3,"")))
E13: =IF(D13="Gross",0,IF(D13="Registered",0.2,IF(D13="Unregistered",0.3,"")))
... E101: =IF(D101="Gross",0,IF(D101="Registered",0.2,IF(D101="Unregistered",0.3,"")))

Sheet Payments
A1: Payment date | B1: Subcontractor | C1: Labour £ | D1: Materials £ | E1: VAT £ | F1: Tax month ends | G1: Rate | H1: CIS deduction £ | I1: Pay subcontractor £ | K1: Unknown subcontractor → 30% until verified. Deduction is on labour only (not materials, VAT or CITB levy).
F2: =IF(A2="","",IF(DAY(A2)<=5,DATE(YEAR(A2),MONTH(A2),5),DATE(YEAR(A2),MONTH(A2)+1,5))) | G2: =IF(B2="","",IFERROR(INDEX(Subcontractors!$E$2:$E$101,MATCH(B2,Subcontractors!$A$2:$A$101,0)),0.3)) | H2: =IF(B2="","",ROUND(N(C2)*G2,2)) | I2: =IF(B2="","",N(C2)+N(D2)+N(E2)-H2)
F3: =IF(A3="","",IF(DAY(A3)<=5,DATE(YEAR(A3),MONTH(A3),5),DATE(YEAR(A3),MONTH(A3)+1,5))) | G3: =IF(B3="","",IFERROR(INDEX(Subcontractors!$E$2:$E$101,MATCH(B3,Subcontractors!$A$2:$A$101,0)),0.3)) | H3: =IF(B3="","",ROUND(N(C3)*G3,2)) | I3: =IF(B3="","",N(C3)+N(D3)+N(E3)-H3)
F4: =IF(A4="","",IF(DAY(A4)<=5,DATE(YEAR(A4),MONTH(A4),5),DATE(YEAR(A4),MONTH(A4)+1,5))) | G4: =IF(B4="","",IFERROR(INDEX(Subcontractors!$E$2:$E$101,MATCH(B4,Subcontractors!$A$2:$A$101,0)),0.3)) | H4: =IF(B4="","",ROUND(N(C4)*G4,2)) | I4: =IF(B4="","",N(C4)+N(D4)+N(E4)-H4)
F5: =IF(A5="","",IF(DAY(A5)<=5,DATE(YEAR(A5),MONTH(A5),5),DATE(YEAR(A5),MONTH(A5)+1,5))) | G5: =IF(B5="","",IFERROR(INDEX(Subcontractors!$E$2:$E$101,MATCH(B5,Subcontractors!$A$2:$A$101,0)),0.3)) | H5: =IF(B5="","",ROUND(N(C5)*G5,2)) | I5: =IF(B5="","",N(C5)+N(D5)+N(E5)-H5)
F6: =IF(A6="","",IF(DAY(A6)<=5,DATE(YEAR(A6),MONTH(A6),5),DATE(YEAR(A6),MONTH(A6)+1,5))) | G6: =IF(B6="","",IFERROR(INDEX(Subcontractors!$E$2:$E$101,MATCH(B6,Subcontractors!$A$2:$A$101,0)),0.3)) | H6: =IF(B6="","",ROUND(N(C6)*G6,2)) | I6: =IF(B6="","",N(C6)+N(D6)+N(E6)-H6)
F7: =IF(A7="","",IF(DAY(A7)<=5,DATE(YEAR(A7),MONTH(A7),5),DATE(YEAR(A7),MONTH(A7)+1,5))) | G7: =IF(B7="","",IFERROR(INDEX(Subcontractors!$E$2:$E$101,MATCH(B7,Subcontractors!$A$2:$A$101,0)),0.3)) | H7: =IF(B7="","",ROUND(N(C7)*G7,2)) | I7: =IF(B7="","",N(C7)+N(D7)+N(E7)-H7)
F8: =IF(A8="","",IF(DAY(A8)<=5,DATE(YEAR(A8),MONTH(A8),5),DATE(YEAR(A8),MONTH(A8)+1,5))) | G8: =IF(B8="","",IFERROR(INDEX(Subcontractors!$E$2:$E$101,MATCH(B8,Subcontractors!$A$2:$A$101,0)),0.3)) | H8: =IF(B8="","",ROUND(N(C8)*G8,2)) | I8: =IF(B8="","",N(C8)+N(D8)+N(E8)-H8)
F9: =IF(A9="","",IF(DAY(A9)<=5,DATE(YEAR(A9),MONTH(A9),5),DATE(YEAR(A9),MONTH(A9)+1,5))) | G9: =IF(B9="","",IFERROR(INDEX(Subcontractors!$E$2:$E$101,MATCH(B9,Subcontractors!$A$2:$A$101,0)),0.3)) | H9: =IF(B9="","",ROUND(N(C9)*G9,2)) | I9: =IF(B9="","",N(C9)+N(D9)+N(E9)-H9)
F10: =IF(A10="","",IF(DAY(A10)<=5,DATE(YEAR(A10),MONTH(A10),5),DATE(YEAR(A10),MONTH(A10)+1,5))) | G10: =IF(B10="","",IFERROR(INDEX(Subcontractors!$E$2:$E$101,MATCH(B10,Subcontractors!$A$2:$A$101,0)),0.3)) | H10: =IF(B10="","",ROUND(N(C10)*G10,2)) | I10: =IF(B10="","",N(C10)+N(D10)+N(E10)-H10)
F11: =IF(A11="","",IF(DAY(A11)<=5,DATE(YEAR(A11),MONTH(A11),5),DATE(YEAR(A11),MONTH(A11)+1,5))) | G11: =IF(B11="","",IFERROR(INDEX(Subcontractors!$E$2:$E$101,MATCH(B11,Subcontractors!$A$2:$A$101,0)),0.3)) | H11: =IF(B11="","",ROUND(N(C11)*G11,2)) | I11: =IF(B11="","",N(C11)+N(D11)+N(E11)-H11)
F12: =IF(A12="","",IF(DAY(A12)<=5,DATE(YEAR(A12),MONTH(A12),5),DATE(YEAR(A12),MONTH(A12)+1,5))) | G12: =IF(B12="","",IFERROR(INDEX(Subcontractors!$E$2:$E$101,MATCH(B12,Subcontractors!$A$2:$A$101,0)),0.3)) | H12: =IF(B12="","",ROUND(N(C12)*G12,2)) | I12: =IF(B12="","",N(C12)+N(D12)+N(E12)-H12)
F13: =IF(A13="","",IF(DAY(A13)<=5,DATE(YEAR(A13),MONTH(A13),5),DATE(YEAR(A13),MONTH(A13)+1,5))) | G13: =IF(B13="","",IFERROR(INDEX(Subcontractors!$E$2:$E$101,MATCH(B13,Subcontractors!$A$2:$A$101,0)),0.3)) | H13: =IF(B13="","",ROUND(N(C13)*G13,2)) | I13: =IF(B13="","",N(C13)+N(D13)+N(E13)-H13)
... F501: =IF(A501="","",IF(DAY(A501)<=5,DATE(YEAR(A501),MONTH(A501),5),DATE(YEAR(A501),MONTH(A501)+1,5))) | G501: =IF(B501="","",IFERROR(INDEX(Subcontractors!$E$2:$E$101,MATCH(B501,Subcontractors!$A$2:$A$101,0)),0.3)) | H501: =IF(B501="","",ROUND(N(C501)*G501,2)) | I501: =IF(B501="","",N(C501)+N(D501)+N(E501)-H501)

Sheet Monthly return
A1: Tax month ends | B1: Return due | C1: Pay HMRC by (electronic) | D1: Labour paid £ | E1: Materials £ | F1: CIS deducted £ | G1: Days to return | I1: File a return every month you're registered as a contractor, including a nil return if you paid nobody (or tell HMRC you're inactive).
A2: =DATE(2026,5,5) | B2: =A2+14 | C2: =A2+17 | D2: =SUMIFS(Payments!$C:$C,Payments!$F:$F,A2) | E2: =SUMIFS(Payments!$D:$D,Payments!$F:$F,A2) | F2: =SUMIFS(Payments!$H:$H,Payments!$F:$F,A2) | G2: =B2-TODAY()
A3: =DATE(2026,6,5) | B3: =A3+14 | C3: =A3+17 | D3: =SUMIFS(Payments!$C:$C,Payments!$F:$F,A3) | E3: =SUMIFS(Payments!$D:$D,Payments!$F:$F,A3) | F3: =SUMIFS(Payments!$H:$H,Payments!$F:$F,A3) | G3: =B3-TODAY()
A4: =DATE(2026,7,5) | B4: =A4+14 | C4: =A4+17 | D4: =SUMIFS(Payments!$C:$C,Payments!$F:$F,A4) | E4: =SUMIFS(Payments!$D:$D,Payments!$F:$F,A4) | F4: =SUMIFS(Payments!$H:$H,Payments!$F:$F,A4) | G4: =B4-TODAY()
A5: =DATE(2026,8,5) | B5: =A5+14 | C5: =A5+17 | D5: =SUMIFS(Payments!$C:$C,Payments!$F:$F,A5) | E5: =SUMIFS(Payments!$D:$D,Payments!$F:$F,A5) | F5: =SUMIFS(Payments!$H:$H,Payments!$F:$F,A5) | G5: =B5-TODAY()
A6: =DATE(2026,9,5) | B6: =A6+14 | C6: =A6+17 | D6: =SUMIFS(Payments!$C:$C,Payments!$F:$F,A6) | E6: =SUMIFS(Payments!$D:$D,Payments!$F:$F,A6) | F6: =SUMIFS(Payments!$H:$H,Payments!$F:$F,A6) | G6: =B6-TODAY()
A7: =DATE(2026,10,5) | B7: =A7+14 | C7: =A7+17 | D7: =SUMIFS(Payments!$C:$C,Payments!$F:$F,A7) | E7: =SUMIFS(Payments!$D:$D,Payments!$F:$F,A7) | F7: =SUMIFS(Payments!$H:$H,Payments!$F:$F,A7) | G7: =B7-TODAY()
A8: =DATE(2026,11,5) | B8: =A8+14 | C8: =A8+17 | D8: =SUMIFS(Payments!$C:$C,Payments!$F:$F,A8) | E8: =SUMIFS(Payments!$D:$D,Payments!$F:$F,A8) | F8: =SUMIFS(Payments!$H:$H,Payments!$F:$F,A8) | G8: =B8-TODAY()
A9: =DATE(2026,12,5) | B9: =A9+14 | C9: =A9+17 | D9: =SUMIFS(Payments!$C:$C,Payments!$F:$F,A9) | E9: =SUMIFS(Payments!$D:$D,Payments!$F:$F,A9) | F9: =SUMIFS(Payments!$H:$H,Payments!$F:$F,A9) | G9: =B9-TODAY()
A10: =DATE(2026,13,5) | B10: =A10+14 | C10: =A10+17 | D10: =SUMIFS(Payments!$C:$C,Payments!$F:$F,A10) | E10: =SUMIFS(Payments!$D:$D,Payments!$F:$F,A10) | F10: =SUMIFS(Payments!$H:$H,Payments!$F:$F,A10) | G10: =B10-TODAY()
A11: =DATE(2026,14,5) | B11: =A11+14 | C11: =A11+17 | D11: =SUMIFS(Payments!$C:$C,Payments!$F:$F,A11) | E11: =SUMIFS(Payments!$D:$D,Payments!$F:$F,A11) | F11: =SUMIFS(Payments!$H:$H,Payments!$F:$F,A11) | G11: =B11-TODAY()
A12: =DATE(2026,15,5) | B12: =A12+14 | C12: =A12+17 | D12: =SUMIFS(Payments!$C:$C,Payments!$F:$F,A12) | E12: =SUMIFS(Payments!$D:$D,Payments!$F:$F,A12) | F12: =SUMIFS(Payments!$H:$H,Payments!$F:$F,A12) | G12: =B12-TODAY()
A13: =DATE(2026,16,5) | B13: =A13+14 | C13: =A13+17 | D13: =SUMIFS(Payments!$C:$C,Payments!$F:$F,A13) | E13: =SUMIFS(Payments!$D:$D,Payments!$F:$F,A13) | F13: =SUMIFS(Payments!$H:$H,Payments!$F:$F,A13) | G13: =B13-TODAY()

Sheet Statement
A1: CIS payment and deduction statement
A3: Contractor name
A4: Contractor employer's reference
A5: Subcontractor
A6: Subcontractor verification number
A7: Tax month ending
A8: Gross amount paid (excl. VAT) £ | B8: =SUMIFS(Payments!$C:$C,Payments!$B:$B,B5,Payments!$F:$F,B7)+SUMIFS(Payments!$D:$D,Payments!$B:$B,B5,Payments!$F:$F,B7)
A9: Cost of materials £ | B9: =SUMIFS(Payments!$D:$D,Payments!$B:$B,B5,Payments!$F:$F,B7)
A10: Amount liable to deduction £ | B10: =B8-B9
A11: Amount deducted £ | B11: =SUMIFS(Payments!$H:$H,Payments!$B:$B,B5,Payments!$F:$F,B7)
A13: Give this to the subcontractor within 14 days of the end of the tax month. Keep a copy.

Sheet Deductions suffered
A1: Date | B1: Contractor | C1: Gross paid £ | D1: Materials £ | E1: CIS deducted £ | F1: Statement received? | H1: Total deducted £ | I1: =SUM(E2:E201)
H2: Enter this total in your Self Assessment ('CIS deductions') to reduce your tax bill or get a refund.

Sheet DRC invoice
A1: VAT INVOICE – DOMESTIC REVERSE CHARGE
A3: Your business name
A4: Your address
A5: Your VAT number
A6: Customer name
A7: Customer address
A8: Customer VAT number
A9: Invoice number
A10: Invoice date / tax point
A12: Description (mark reverse charge items) | B12: Qty | C12: Unit £ | D12: VAT rate | E12: Net £
E13: =IF(B13="","",B13*C13) | F13: =IF(E13="",0,E13*N(D13))
E14: =IF(B14="","",B14*C14) | F14: =IF(E14="",0,E14*N(D14))
E15: =IF(B15="","",B15*C15) | F15: =IF(E15="",0,E15*N(D15))
E16: =IF(B16="","",B16*C16) | F16: =IF(E16="",0,E16*N(D16))
E17: =IF(B17="","",B17*C17) | F17: =IF(E17="",0,E17*N(D17))
E18: =IF(B18="","",B18*C18) | F18: =IF(E18="",0,E18*N(D18))
E19: =IF(B19="","",B19*C19) | F19: =IF(E19="",0,E19*N(D19))
E20: =IF(B20="","",B20*C20) | F20: =IF(E20="",0,E20*N(D20))
D22: Total (net) £ | E22: =SUM(E13:E20)
D23: VAT to be accounted for by customer £ | E23: =SUM(F13:F20)
D24: Amount payable £ | E24: =E22
A26: Reverse charge: Customer to account to HMRC for the reverse charge output tax on the VAT exclusive price of items marked 'reverse charge'.
A28: Use only when the customer is VAT- and CIS-registered and is not an end user or intermediary. Enter the VAT rate (e.g. 0.2) so the customer can see the VAT they account for. A record-keeping aid, not tax advice. Check gov.uk/what-is-the-construction-industry-scheme and HMRC's VAT reverse charge guidance.
