Workbook

Sheet Start here
A1: MTD Ready for Landlords – UK property income workbook, tax year 2026-27
A2: This workbook helps landlords keep digital records. It is not HMRC-recognised software and cannot submit to HMRC by itself: use HMRC-recognised bridging software to send quarterly updates from a spreadsheet. It is not tax advice. Check gov.uk or an accountant for your circumstances.
A4: How to use
A5: 1. Settings: choose Standard (6 Apr) or Calendar (1 Apr) quarters.
A6: 2. Income: one row per rent receipt or other property income. Jointly owned? Enter only your share.
A7: 3. Expenses: one row per cost; put any personal element in 'Private use £'.
A8: 4. Mortgage interest: record it on the 'Residential finance costs' sheet, not as an expense (see why there).
A9: 5. Quarterly summary shows the cumulative totals your bridging software asks for.
A11: Who must use MTD for Income Tax
A12: Gross self-employment + gross property income over £50,000 (2024-25 return) → from 6 April 2026; over £30,000 → 6 April 2027; over £20,000 → 6 April 2028.
A13: Property allowance: if your gross property income is £1,000 or less you may not need to report it; above that you can deduct £1,000 instead of actual expenses.
A14: Furnished holiday lettings rules ended on 6 April 2025; holiday lets are now treated like other property income.
A16: Facts checked against gov.uk on 25 September 2026. Buyers get free updates for 12 months.

Sheet Settings
A1: Settings
A3: Business name
A4: Quarter basis (Standard / Calendar) | B4: Standard
A6: Quarter | B6: Start | C6: End
A7: Q1 | B7: =IF($B$4="Calendar",DATE(2026,4,1),DATE(2026,4,6)) | C7: =IF($B$4="Calendar",DATE(2026,6,30),DATE(2026,7,5))
A8: Q2 | B8: =IF($B$4="Calendar",DATE(2026,7,1),DATE(2026,7,6)) | C8: =IF($B$4="Calendar",DATE(2026,9,30),DATE(2026,10,5))
A9: Q3 | B9: =IF($B$4="Calendar",DATE(2026,10,1),DATE(2026,10,6)) | C9: =IF($B$4="Calendar",DATE(2026,12,31),DATE(2027,1,5))
A10: Q4 | B10: =IF($B$4="Calendar",DATE(2027,1,1),DATE(2027,1,6)) | C10: =IF($B$4="Calendar",DATE(2027,3,31),DATE(2027,4,5))

Sheet Income
A1: Date | B1: Description | C1: Category | D1: Amount £ | E1: Property / tenant

Sheet Expenses
A1: Date | B1: Supplier | C1: Description | D1: Category | E1: Amount £ | F1: Private use £ | G1: Business part £
G2: =IF(E2="","",E2-N(F2))
G3: =IF(E3="","",E3-N(F3))
G4: =IF(E4="","",E4-N(F4))
G5: =IF(E5="","",E5-N(F5))
G6: =IF(E6="","",E6-N(F6))
G7: =IF(E7="","",E7-N(F7))
G8: =IF(E8="","",E8-N(F8))
G9: =IF(E9="","",E9-N(F9))
G10: =IF(E10="","",E10-N(F10))
G11: =IF(E11="","",E11-N(F11))
G12: =IF(E12="","",E12-N(F12))
G13: =IF(E13="","",E13-N(F13))
... G1001: =IF(E1001="","",E1001-N(F1001))

Sheet Residential finance costs
A1: Date | B1: Lender | C1: Property | D1: Interest and finance costs £ | F1: Year total £ | G1: =SUM(D2:D201)
F2: Estimated 20% tax credit £ | G2: =G1*0.2
F4: Mortgage interest on residential lets is not deducted from rental profit. Instead you get a tax credit of 20% of these costs (the credit can be limited; see gov.uk 'restricting finance cost relief').

Sheet Mileage
A1: Date | B1: From | C1: To | D1: Business purpose | E1: Miles | F1: Miles so far this year | G1: Allowance £ | I1: Cars and vans: 45p/mile first 10,000 business miles, then 25p. Motorcycles: 24p (not calculated here).
F2: =IF(E2="",0,0+E2) | G2: =IF(E2="","",MIN(E2,MAX(0,10000-0))*0.45+MAX(0,E2-MAX(0,10000-0))*0.25) | I2: You cannot claim mileage and actual running costs for the same vehicle. Source: gov.uk/simpler-income-tax-simplified-expenses
F3: =IF(E3="",F2,F2+E3) | G3: =IF(E3="","",MIN(E3,MAX(0,10000-F2))*0.45+MAX(0,E3-MAX(0,10000-F2))*0.25)
F4: =IF(E4="",F3,F3+E4) | G4: =IF(E4="","",MIN(E4,MAX(0,10000-F3))*0.45+MAX(0,E4-MAX(0,10000-F3))*0.25)
F5: =IF(E5="",F4,F4+E5) | G5: =IF(E5="","",MIN(E5,MAX(0,10000-F4))*0.45+MAX(0,E5-MAX(0,10000-F4))*0.25)
F6: =IF(E6="",F5,F5+E6) | G6: =IF(E6="","",MIN(E6,MAX(0,10000-F5))*0.45+MAX(0,E6-MAX(0,10000-F5))*0.25)
F7: =IF(E7="",F6,F6+E7) | G7: =IF(E7="","",MIN(E7,MAX(0,10000-F6))*0.45+MAX(0,E7-MAX(0,10000-F6))*0.25)
F8: =IF(E8="",F7,F7+E8) | G8: =IF(E8="","",MIN(E8,MAX(0,10000-F7))*0.45+MAX(0,E8-MAX(0,10000-F7))*0.25)
F9: =IF(E9="",F8,F8+E9) | G9: =IF(E9="","",MIN(E9,MAX(0,10000-F8))*0.45+MAX(0,E9-MAX(0,10000-F8))*0.25)
F10: =IF(E10="",F9,F9+E10) | G10: =IF(E10="","",MIN(E10,MAX(0,10000-F9))*0.45+MAX(0,E10-MAX(0,10000-F9))*0.25)
F11: =IF(E11="",F10,F10+E11) | G11: =IF(E11="","",MIN(E11,MAX(0,10000-F10))*0.45+MAX(0,E11-MAX(0,10000-F10))*0.25)
F12: =IF(E12="",F11,F11+E12) | G12: =IF(E12="","",MIN(E12,MAX(0,10000-F11))*0.45+MAX(0,E12-MAX(0,10000-F11))*0.25)
F13: =IF(E13="",F12,F12+E13) | G13: =IF(E13="","",MIN(E13,MAX(0,10000-F12))*0.45+MAX(0,E13-MAX(0,10000-F12))*0.25)
F14: =IF(E14="",F13,F13+E14) | G14: =IF(E14="","",MIN(E14,MAX(0,10000-F13))*0.45+MAX(0,E14-MAX(0,10000-F13))*0.25)
... F1001: =IF(E1001="",F1000,F1000+E1001) | G1001: =IF(E1001="","",MIN(E1001,MAX(0,10000-F1000))*0.45+MAX(0,E1001-MAX(0,10000-F1000))*0.25)

Sheet Use of home
A1: Month | B1: Hours worked at home | C1: Flat rate £ | E1: HMRC flat rates: 25-50 hours £10/month, 51-100 £18, 101+ £26. Source: gov.uk/simpler-income-tax-simplified-expenses
A2: Apr 2026 | C2: =IF(B2>=101,26,IF(B2>=51,18,IF(B2>=25,10,0)))
A3: May 2026 | C3: =IF(B3>=101,26,IF(B3>=51,18,IF(B3>=25,10,0)))
A4: Jun 2026 | C4: =IF(B4>=101,26,IF(B4>=51,18,IF(B4>=25,10,0)))
A5: Jul 2026 | C5: =IF(B5>=101,26,IF(B5>=51,18,IF(B5>=25,10,0)))
A6: Aug 2026 | C6: =IF(B6>=101,26,IF(B6>=51,18,IF(B6>=25,10,0)))
A7: Sep 2026 | C7: =IF(B7>=101,26,IF(B7>=51,18,IF(B7>=25,10,0)))
A8: Oct 2026 | C8: =IF(B8>=101,26,IF(B8>=51,18,IF(B8>=25,10,0)))
A9: Nov 2026 | C9: =IF(B9>=101,26,IF(B9>=51,18,IF(B9>=25,10,0)))
A10: Dec 2026 | C10: =IF(B10>=101,26,IF(B10>=51,18,IF(B10>=25,10,0)))
A11: Jan 2027 | C11: =IF(B11>=101,26,IF(B11>=51,18,IF(B11>=25,10,0)))
A12: Feb 2027 | C12: =IF(B12>=101,26,IF(B12>=51,18,IF(B12>=25,10,0)))
A13: Mar 2027 | C13: =IF(B13>=101,26,IF(B13>=51,18,IF(B13>=25,10,0)))
A14: Total | C14: =SUM(C2:C13)

Sheet Quarterly summary
A1: Quarterly summary – copy these into your bridging software
A2: Quarterly updates are cumulative: HMRC asks for totals from the start of the tax year.
A4: Category | B4: Q1 | C4: Q2 | D4: Q3 | E4: Q4 | F4: YTD to Q1 | G4: YTD to Q2 | H4: YTD to Q3 | I4: YTD to Q4
A5: INCOME
A6: Rent received | B6: =SUMIFS(Income!$D:$D,Income!$C:$C,"Rent received",Income!$A:$A,">="&Settings!$B$7,Income!$A:$A,"<="&Settings!$C$7) | C6: =SUMIFS(Income!$D:$D,Income!$C:$C,"Rent received",Income!$A:$A,">="&Settings!$B$8,Income!$A:$A,"<="&Settings!$C$8) | D6: =SUMIFS(Income!$D:$D,Income!$C:$C,"Rent received",Income!$A:$A,">="&Settings!$B$9,Income!$A:$A,"<="&Settings!$C$9) | E6: =SUMIFS(Income!$D:$D,Income!$C:$C,"Rent received",Income!$A:$A,">="&Settings!$B$10,Income!$A:$A,"<="&Settings!$C$10) | F6: =SUMIFS(Income!$D:$D,Income!$C:$C,"Rent received",Income!$A:$A,">="&Settings!$B$7,Income!$A:$A,"<="&Settings!$C$7) | G6: =SUMIFS(Income!$D:$D,Income!$C:$C,"Rent received",Income!$A:$A,">="&Settings!$B$7,Income!$A:$A,"<="&Settings!$C$8) | H6: =SUMIFS(Income!$D:$D,Income!$C:$C,"Rent received",Income!$A:$A,">="&Settings!$B$7,Income!$A:$A,"<="&Settings!$C$9) | I6: =SUMIFS(Income!$D:$D,Income!$C:$C,"Rent received",Income!$A:$A,">="&Settings!$B$7,Income!$A:$A,"<="&Settings!$C$10)
A7: Premiums for the grant of a lease | B7: =SUMIFS(Income!$D:$D,Income!$C:$C,"Premiums for the grant of a lease",Income!$A:$A,">="&Settings!$B$7,Income!$A:$A,"<="&Settings!$C$7) | C7: =SUMIFS(Income!$D:$D,Income!$C:$C,"Premiums for the grant of a lease",Income!$A:$A,">="&Settings!$B$8,Income!$A:$A,"<="&Settings!$C$8) | D7: =SUMIFS(Income!$D:$D,Income!$C:$C,"Premiums for the grant of a lease",Income!$A:$A,">="&Settings!$B$9,Income!$A:$A,"<="&Settings!$C$9) | E7: =SUMIFS(Income!$D:$D,Income!$C:$C,"Premiums for the grant of a lease",Income!$A:$A,">="&Settings!$B$10,Income!$A:$A,"<="&Settings!$C$10) | F7: =SUMIFS(Income!$D:$D,Income!$C:$C,"Premiums for the grant of a lease",Income!$A:$A,">="&Settings!$B$7,Income!$A:$A,"<="&Settings!$C$7) | G7: =SUMIFS(Income!$D:$D,Income!$C:$C,"Premiums for the grant of a lease",Income!$A:$A,">="&Settings!$B$7,Income!$A:$A,"<="&Settings!$C$8) | H7: =SUMIFS(Income!$D:$D,Income!$C:$C,"Premiums for the grant of a lease",Income!$A:$A,">="&Settings!$B$7,Income!$A:$A,"<="&Settings!$C$9) | I7: =SUMIFS(Income!$D:$D,Income!$C:$C,"Premiums for the grant of a lease",Income!$A:$A,">="&Settings!$B$7,Income!$A:$A,"<="&Settings!$C$10)
A8: Reverse premiums and inducements | B8: =SUMIFS(Income!$D:$D,Income!$C:$C,"Reverse premiums and inducements",Income!$A:$A,">="&Settings!$B$7,Income!$A:$A,"<="&Settings!$C$7) | C8: =SUMIFS(Income!$D:$D,Income!$C:$C,"Reverse premiums and inducements",Income!$A:$A,">="&Settings!$B$8,Income!$A:$A,"<="&Settings!$C$8) | D8: =SUMIFS(Income!$D:$D,Income!$C:$C,"Reverse premiums and inducements",Income!$A:$A,">="&Settings!$B$9,Income!$A:$A,"<="&Settings!$C$9) | E8: =SUMIFS(Income!$D:$D,Income!$C:$C,"Reverse premiums and inducements",Income!$A:$A,">="&Settings!$B$10,Income!$A:$A,"<="&Settings!$C$10) | F8: =SUMIFS(Income!$D:$D,Income!$C:$C,"Reverse premiums and inducements",Income!$A:$A,">="&Settings!$B$7,Income!$A:$A,"<="&Settings!$C$7) | G8: =SUMIFS(Income!$D:$D,Income!$C:$C,"Reverse premiums and inducements",Income!$A:$A,">="&Settings!$B$7,Income!$A:$A,"<="&Settings!$C$8) | H8: =SUMIFS(Income!$D:$D,Income!$C:$C,"Reverse premiums and inducements",Income!$A:$A,">="&Settings!$B$7,Income!$A:$A,"<="&Settings!$C$9) | I8: =SUMIFS(Income!$D:$D,Income!$C:$C,"Reverse premiums and inducements",Income!$A:$A,">="&Settings!$B$7,Income!$A:$A,"<="&Settings!$C$10)
A9: Other property income | B9: =SUMIFS(Income!$D:$D,Income!$C:$C,"Other property income",Income!$A:$A,">="&Settings!$B$7,Income!$A:$A,"<="&Settings!$C$7) | C9: =SUMIFS(Income!$D:$D,Income!$C:$C,"Other property income",Income!$A:$A,">="&Settings!$B$8,Income!$A:$A,"<="&Settings!$C$8) | D9: =SUMIFS(Income!$D:$D,Income!$C:$C,"Other property income",Income!$A:$A,">="&Settings!$B$9,Income!$A:$A,"<="&Settings!$C$9) | E9: =SUMIFS(Income!$D:$D,Income!$C:$C,"Other property income",Income!$A:$A,">="&Settings!$B$10,Income!$A:$A,"<="&Settings!$C$10) | F9: =SUMIFS(Income!$D:$D,Income!$C:$C,"Other property income",Income!$A:$A,">="&Settings!$B$7,Income!$A:$A,"<="&Settings!$C$7) | G9: =SUMIFS(Income!$D:$D,Income!$C:$C,"Other property income",Income!$A:$A,">="&Settings!$B$7,Income!$A:$A,"<="&Settings!$C$8) | H9: =SUMIFS(Income!$D:$D,Income!$C:$C,"Other property income",Income!$A:$A,">="&Settings!$B$7,Income!$A:$A,"<="&Settings!$C$9) | I9: =SUMIFS(Income!$D:$D,Income!$C:$C,"Other property income",Income!$A:$A,">="&Settings!$B$7,Income!$A:$A,"<="&Settings!$C$10)
A11: EXPENSES (business part only)
A12: Rent, rates, insurance and ground rents | B12: =SUMIFS(Expenses!$G:$G,Expenses!$D:$D,"Rent, rates, insurance and ground rents",Expenses!$A:$A,">="&Settings!$B$7,Expenses!$A:$A,"<="&Settings!$C$7) | C12: =SUMIFS(Expenses!$G:$G,Expenses!$D:$D,"Rent, rates, insurance and ground rents",Expenses!$A:$A,">="&Settings!$B$8,Expenses!$A:$A,"<="&Settings!$C$8) | D12: =SUMIFS(Expenses!$G:$G,Expenses!$D:$D,"Rent, rates, insurance and ground rents",Expenses!$A:$A,">="&Settings!$B$9,Expenses!$A:$A,"<="&Settings!$C$9) | E12: =SUMIFS(Expenses!$G:$G,Expenses!$D:$D,"Rent, rates, insurance and ground rents",Expenses!$A:$A,">="&Settings!$B$10,Expenses!$A:$A,"<="&Settings!$C$10) | F12: =SUMIFS(Expenses!$G:$G,Expenses!$D:$D,"Rent, rates, insurance and ground rents",Expenses!$A:$A,">="&Settings!$B$7,Expenses!$A:$A,"<="&Settings!$C$7) | G12: =SUMIFS(Expenses!$G:$G,Expenses!$D:$D,"Rent, rates, insurance and ground rents",Expenses!$A:$A,">="&Settings!$B$7,Expenses!$A:$A,"<="&Settings!$C$8) | H12: =SUMIFS(Expenses!$G:$G,Expenses!$D:$D,"Rent, rates, insurance and ground rents",Expenses!$A:$A,">="&Settings!$B$7,Expenses!$A:$A,"<="&Settings!$C$9) | I12: =SUMIFS(Expenses!$G:$G,Expenses!$D:$D,"Rent, rates, insurance and ground rents",Expenses!$A:$A,">="&Settings!$B$7,Expenses!$A:$A,"<="&Settings!$C$10)
A13: Property repairs and maintenance | B13: =SUMIFS(Expenses!$G:$G,Expenses!$D:$D,"Property repairs and maintenance",Expenses!$A:$A,">="&Settings!$B$7,Expenses!$A:$A,"<="&Settings!$C$7) | C13: =SUMIFS(Expenses!$G:$G,Expenses!$D:$D,"Property repairs and maintenance",Expenses!$A:$A,">="&Settings!$B$8,Expenses!$A:$A,"<="&Settings!$C$8) | D13: =SUMIFS(Expenses!$G:$G,Expenses!$D:$D,"Property repairs and maintenance",Expenses!$A:$A,">="&Settings!$B$9,Expenses!$A:$A,"<="&Settings!$C$9) | E13: =SUMIFS(Expenses!$G:$G,Expenses!$D:$D,"Property repairs and maintenance",Expenses!$A:$A,">="&Settings!$B$10,Expenses!$A:$A,"<="&Settings!$C$10) | F13: =SUMIFS(Expenses!$G:$G,Expenses!$D:$D,"Property repairs and maintenance",Expenses!$A:$A,">="&Settings!$B$7,Expenses!$A:$A,"<="&Settings!$C$7) | G13: =SUMIFS(Expenses!$G:$G,Expenses!$D:$D,"Property repairs and maintenance",Expenses!$A:$A,">="&Settings!$B$7,Expenses!$A:$A,"<="&Settings!$C$8) | H13: =SUMIFS(Expenses!$G:$G,Expenses!$D:$D,"Property repairs and maintenance",Expenses!$A:$A,">="&Settings!$B$7,Expenses!$A:$A,"<="&Settings!$C$9) | I13: =SUMIFS(Expenses!$G:$G,Expenses!$D:$D,"Property repairs and maintenance",Expenses!$A:$A,">="&Settings!$B$7,Expenses!$A:$A,"<="&Settings!$C$10)
A14: Non-residential property finance costs | B14: =SUMIFS(Expenses!$G:$G,Expenses!$D:$D,"Non-residential property finance costs",Expenses!$A:$A,">="&Settings!$B$7,Expenses!$A:$A,"<="&Settings!$C$7) | C14: =SUMIFS(Expenses!$G:$G,Expenses!$D:$D,"Non-residential property finance costs",Expenses!$A:$A,">="&Settings!$B$8,Expenses!$A:$A,"<="&Settings!$C$8) | D14: =SUMIFS(Expenses!$G:$G,Expenses!$D:$D,"Non-residential property finance costs",Expenses!$A:$A,">="&Settings!$B$9,Expenses!$A:$A,"<="&Settings!$C$9) | E14: =SUMIFS(Expenses!$G:$G,Expenses!$D:$D,"Non-residential property finance costs",Expenses!$A:$A,">="&Settings!$B$10,Expenses!$A:$A,"<="&Settings!$C$10) | F14: =SUMIFS(Expenses!$G:$G,Expenses!$D:$D,"Non-residential property finance costs",Expenses!$A:$A,">="&Settings!$B$7,Expenses!$A:$A,"<="&Settings!$C$7) | G14: =SUMIFS(Expenses!$G:$G,Expenses!$D:$D,"Non-residential property finance costs",Expenses!$A:$A,">="&Settings!$B$7,Expenses!$A:$A,"<="&Settings!$C$8) | H14: =SUMIFS(Expenses!$G:$G,Expenses!$D:$D,"Non-residential property finance costs",Expenses!$A:$A,">="&Settings!$B$7,Expenses!$A:$A,"<="&Settings!$C$9) | I14: =SUMIFS(Expenses!$G:$G,Expenses!$D:$D,"Non-residential property finance costs",Expenses!$A:$A,">="&Settings!$B$7,Expenses!$A:$A,"<="&Settings!$C$10)
A15: Legal, management and other professional fees | B15: =SUMIFS(Expenses!$G:$G,Expenses!$D:$D,"Legal, management and other professional fees",Expenses!$A:$A,">="&Settings!$B$7,Expenses!$A:$A,"<="&Settings!$C$7) | C15: =SUMIFS(Expenses!$G:$G,Expenses!$D:$D,"Legal, management and other professional fees",Expenses!$A:$A,">="&Settings!$B$8,Expenses!$A:$A,"<="&Settings!$C$8) | D15: =SUMIFS(Expenses!$G:$G,Expenses!$D:$D,"Legal, management and other professional fees",Expenses!$A:$A,">="&Settings!$B$9,Expenses!$A:$A,"<="&Settings!$C$9) | E15: =SUMIFS(Expenses!$G:$G,Expenses!$D:$D,"Legal, management and other professional fees",Expenses!$A:$A,">="&Settings!$B$10,Expenses!$A:$A,"<="&Settings!$C$10) | F15: =SUMIFS(Expenses!$G:$G,Expenses!$D:$D,"Legal, management and other professional fees",Expenses!$A:$A,">="&Settings!$B$7,Expenses!$A:$A,"<="&Settings!$C$7) | G15: =SUMIFS(Expenses!$G:$G,Expenses!$D:$D,"Legal, management and other professional fees",Expenses!$A:$A,">="&Settings!$B$7,Expenses!$A:$A,"<="&Settings!$C$8) | H15: =SUMIFS(Expenses!$G:$G,Expenses!$D:$D,"Legal, management and other professional fees",Expenses!$A:$A,">="&Settings!$B$7,Expenses!$A:$A,"<="&Settings!$C$9) | I15: =SUMIFS(Expenses!$G:$G,Expenses!$D:$D,"Legal, management and other professional fees",Expenses!$A:$A,">="&Settings!$B$7,Expenses!$A:$A,"<="&Settings!$C$10)
A16: Costs of services provided, including wages | B16: =SUMIFS(Expenses!$G:$G,Expenses!$D:$D,"Costs of services provided, including wages",Expenses!$A:$A,">="&Settings!$B$7,Expenses!$A:$A,"<="&Settings!$C$7) | C16: =SUMIFS(Expenses!$G:$G,Expenses!$D:$D,"Costs of services provided, including wages",Expenses!$A:$A,">="&Settings!$B$8,Expenses!$A:$A,"<="&Settings!$C$8) | D16: =SUMIFS(Expenses!$G:$G,Expenses!$D:$D,"Costs of services provided, including wages",Expenses!$A:$A,">="&Settings!$B$9,Expenses!$A:$A,"<="&Settings!$C$9) | E16: =SUMIFS(Expenses!$G:$G,Expenses!$D:$D,"Costs of services provided, including wages",Expenses!$A:$A,">="&Settings!$B$10,Expenses!$A:$A,"<="&Settings!$C$10) | F16: =SUMIFS(Expenses!$G:$G,Expenses!$D:$D,"Costs of services provided, including wages",Expenses!$A:$A,">="&Settings!$B$7,Expenses!$A:$A,"<="&Settings!$C$7) | G16: =SUMIFS(Expenses!$G:$G,Expenses!$D:$D,"Costs of services provided, including wages",Expenses!$A:$A,">="&Settings!$B$7,Expenses!$A:$A,"<="&Settings!$C$8) | H16: =SUMIFS(Expenses!$G:$G,Expenses!$D:$D,"Costs of services provided, including wages",Expenses!$A:$A,">="&Settings!$B$7,Expenses!$A:$A,"<="&Settings!$C$9) | I16: =SUMIFS(Expenses!$G:$G,Expenses!$D:$D,"Costs of services provided, including wages",Expenses!$A:$A,">="&Settings!$B$7,Expenses!$A:$A,"<="&Settings!$C$10)
A17: Travel costs | B17: =SUMIFS(Expenses!$G:$G,Expenses!$D:$D,"Travel costs",Expenses!$A:$A,">="&Settings!$B$7,Expenses!$A:$A,"<="&Settings!$C$7) | C17: =SUMIFS(Expenses!$G:$G,Expenses!$D:$D,"Travel costs",Expenses!$A:$A,">="&Settings!$B$8,Expenses!$A:$A,"<="&Settings!$C$8) | D17: =SUMIFS(Expenses!$G:$G,Expenses!$D:$D,"Travel costs",Expenses!$A:$A,">="&Settings!$B$9,Expenses!$A:$A,"<="&Settings!$C$9) | E17: =SUMIFS(Expenses!$G:$G,Expenses!$D:$D,"Travel costs",Expenses!$A:$A,">="&Settings!$B$10,Expenses!$A:$A,"<="&Settings!$C$10) | F17: =SUMIFS(Expenses!$G:$G,Expenses!$D:$D,"Travel costs",Expenses!$A:$A,">="&Settings!$B$7,Expenses!$A:$A,"<="&Settings!$C$7) | G17: =SUMIFS(Expenses!$G:$G,Expenses!$D:$D,"Travel costs",Expenses!$A:$A,">="&Settings!$B$7,Expenses!$A:$A,"<="&Settings!$C$8) | H17: =SUMIFS(Expenses!$G:$G,Expenses!$D:$D,"Travel costs",Expenses!$A:$A,">="&Settings!$B$7,Expenses!$A:$A,"<="&Settings!$C$9) | I17: =SUMIFS(Expenses!$G:$G,Expenses!$D:$D,"Travel costs",Expenses!$A:$A,">="&Settings!$B$7,Expenses!$A:$A,"<="&Settings!$C$10)
A18: Other allowable property expenses | B18: =SUMIFS(Expenses!$G:$G,Expenses!$D:$D,"Other allowable property expenses",Expenses!$A:$A,">="&Settings!$B$7,Expenses!$A:$A,"<="&Settings!$C$7) | C18: =SUMIFS(Expenses!$G:$G,Expenses!$D:$D,"Other allowable property expenses",Expenses!$A:$A,">="&Settings!$B$8,Expenses!$A:$A,"<="&Settings!$C$8) | D18: =SUMIFS(Expenses!$G:$G,Expenses!$D:$D,"Other allowable property expenses",Expenses!$A:$A,">="&Settings!$B$9,Expenses!$A:$A,"<="&Settings!$C$9) | E18: =SUMIFS(Expenses!$G:$G,Expenses!$D:$D,"Other allowable property expenses",Expenses!$A:$A,">="&Settings!$B$10,Expenses!$A:$A,"<="&Settings!$C$10) | F18: =SUMIFS(Expenses!$G:$G,Expenses!$D:$D,"Other allowable property expenses",Expenses!$A:$A,">="&Settings!$B$7,Expenses!$A:$A,"<="&Settings!$C$7) | G18: =SUMIFS(Expenses!$G:$G,Expenses!$D:$D,"Other allowable property expenses",Expenses!$A:$A,">="&Settings!$B$7,Expenses!$A:$A,"<="&Settings!$C$8) | H18: =SUMIFS(Expenses!$G:$G,Expenses!$D:$D,"Other allowable property expenses",Expenses!$A:$A,">="&Settings!$B$7,Expenses!$A:$A,"<="&Settings!$C$9) | I18: =SUMIFS(Expenses!$G:$G,Expenses!$D:$D,"Other allowable property expenses",Expenses!$A:$A,">="&Settings!$B$7,Expenses!$A:$A,"<="&Settings!$C$10)
A20: Total income | B20: =SUM(B6:B9) | C20: =SUM(C6:C9) | D20: =SUM(D6:D9) | E20: =SUM(E6:E9) | F20: =SUM(F6:F9) | G20: =SUM(G6:G9) | H20: =SUM(H6:H9) | I20: =SUM(I6:I9)
A21: Total expenses | B21: =SUM(B12:B18) | C21: =SUM(C12:C18) | D21: =SUM(D12:D18) | E21: =SUM(E12:E18) | F21: =SUM(F12:F18) | G21: =SUM(G12:G18) | H21: =SUM(H12:H18) | I21: =SUM(I12:I18)
A22: Rental profit before mileage and finance-cost credit | B22: =B20-B21 | C22: =C20-C21 | D22: =D20-D21 | E22: =E20-E21 | F22: =F20-F21 | G22: =G20-G21 | H22: =H20-H21 | I22: =I20-I21
A24: Simplified expenses (add to the category your software asks for)
A25: Mileage allowance (add to 'Travel costs') | B25: =SUMIFS(Mileage!$G:$G,Mileage!$A:$A,">="&Settings!$B$7,Mileage!$A:$A,"<="&Settings!$C$7) | C25: =SUMIFS(Mileage!$G:$G,Mileage!$A:$A,">="&Settings!$B$8,Mileage!$A:$A,"<="&Settings!$C$8) | D25: =SUMIFS(Mileage!$G:$G,Mileage!$A:$A,">="&Settings!$B$9,Mileage!$A:$A,"<="&Settings!$C$9) | E25: =SUMIFS(Mileage!$G:$G,Mileage!$A:$A,">="&Settings!$B$10,Mileage!$A:$A,"<="&Settings!$C$10) | F25: =SUMIFS(Mileage!$G:$G,Mileage!$A:$A,">="&Settings!$B$7,Mileage!$A:$A,"<="&Settings!$C$7) | G25: =SUMIFS(Mileage!$G:$G,Mileage!$A:$A,">="&Settings!$B$7,Mileage!$A:$A,"<="&Settings!$C$8) | H25: =SUMIFS(Mileage!$G:$G,Mileage!$A:$A,">="&Settings!$B$7,Mileage!$A:$A,"<="&Settings!$C$9) | I25: =SUMIFS(Mileage!$G:$G,Mileage!$A:$A,">="&Settings!$B$7,Mileage!$A:$A,"<="&Settings!$C$10)
A29: This workbook helps landlords keep digital records. It is not HMRC-recognised software and cannot submit to HMRC by itself: use HMRC-recognised bridging software to send quarterly updates from a spreadsheet. It is not tax advice. Check gov.uk or an accountant for your circumstances.

Sheet Deadlines
A1: What | B1: Covers | C1: Deadline | D1: Days left
A2: Quarterly update 1 | B2: 6 Apr - 5 Jul 2026 (cumulative) | C2: 46241 | D2: =C2-TODAY()
A3: Quarterly update 2 | B3: Year to 5 Oct 2026 | C3: 46333 | D3: =C3-TODAY()
A4: Quarterly update 3 | B4: Year to 5 Jan 2027 | C4: 46425 | D4: =C4-TODAY()
A5: Quarterly update 4 | B5: Year to 5 Apr 2027 | C5: 46514 | D5: =C5-TODAY()
A6: Final declaration + pay balance | B6: Tax year 2026-27 | C6: 46783 | D6: =C6-TODAY()
A8: Same deadlines apply whether you use standard or calendar quarters. Source: gov.uk (MTD for Income Tax).

Sheet Lists
A1: Income categories | B1: Expense categories
A2: Rent received | B2: Rent, rates, insurance and ground rents
A3: Premiums for the grant of a lease | B3: Property repairs and maintenance
A4: Reverse premiums and inducements | B4: Non-residential property finance costs
A5: Other property income | B5: Legal, management and other professional fees
B6: Costs of services provided, including wages
B7: Travel costs
B8: Other allowable property expenses
