Workbook

Sheet Start here
A1: Online Seller & Side-Hustle Tracker
A2: A record-keeping aid, not tax advice. See gov.uk 'Selling online and paying tax' and 'Tax-free allowances on property and trading income'.
A4: Two different things people mix up:
A5: 1. REPORTING: platforms send HMRC your details if you make 30+ sales or over €2,000 (about £1,700) in a calendar year. That alone is not tax.
A6: 2. TAX: you pay tax only on TRADING (buying or making things to sell for profit), when gross trading income is over the £1,000 trading allowance in a tax year (6 April – 5 April).
A7: Selling your own used clothes and belongings for less than you paid is normally not trading, however many you sell.
A9: How to use
A10: Sales: one row per sale. Mark 'Type' as Personal item or Trading. The Dashboard shows both tests for each platform and year.
A11: Badges of trade: answer the questions if you're unsure whether you're trading.

Sheet Dashboard
A1: Dashboard
A2: Calendar year for platform reporting | B2: 2026
A3: Tax year for the trading allowance | B3: 2026-27
A4: €2,000 in £ (approx.; edit if the rate moves) | B4: 1700
A6: Platform | B6: Sales (calendar yr) | C6: Takings £ (calendar yr) | D6: Likely reported?
A7: eBay | B7: =COUNTIFS(Sales!$B:$B,A7,Sales!$A:$A,">="&DATE($B$2,1,1),Sales!$A:$A,"<="&DATE($B$2,12,31)) | C7: =SUMIFS(Sales!$E:$E,Sales!$B:$B,A7,Sales!$A:$A,">="&DATE($B$2,1,1),Sales!$A:$A,"<="&DATE($B$2,12,31)) | D7: =IF(OR(B7>=30,C7>$B$4),"Yes – expect a report",IF(OR(B7>=24,C7>$B$4*0.8),"Close","No"))
A8: Vinted | B8: =COUNTIFS(Sales!$B:$B,A8,Sales!$A:$A,">="&DATE($B$2,1,1),Sales!$A:$A,"<="&DATE($B$2,12,31)) | C8: =SUMIFS(Sales!$E:$E,Sales!$B:$B,A8,Sales!$A:$A,">="&DATE($B$2,1,1),Sales!$A:$A,"<="&DATE($B$2,12,31)) | D8: =IF(OR(B8>=30,C8>$B$4),"Yes – expect a report",IF(OR(B8>=24,C8>$B$4*0.8),"Close","No"))
A9: Etsy | B9: =COUNTIFS(Sales!$B:$B,A9,Sales!$A:$A,">="&DATE($B$2,1,1),Sales!$A:$A,"<="&DATE($B$2,12,31)) | C9: =SUMIFS(Sales!$E:$E,Sales!$B:$B,A9,Sales!$A:$A,">="&DATE($B$2,1,1),Sales!$A:$A,"<="&DATE($B$2,12,31)) | D9: =IF(OR(B9>=30,C9>$B$4),"Yes – expect a report",IF(OR(B9>=24,C9>$B$4*0.8),"Close","No"))
A10: Depop | B10: =COUNTIFS(Sales!$B:$B,A10,Sales!$A:$A,">="&DATE($B$2,1,1),Sales!$A:$A,"<="&DATE($B$2,12,31)) | C10: =SUMIFS(Sales!$E:$E,Sales!$B:$B,A10,Sales!$A:$A,">="&DATE($B$2,1,1),Sales!$A:$A,"<="&DATE($B$2,12,31)) | D10: =IF(OR(B10>=30,C10>$B$4),"Yes – expect a report",IF(OR(B10>=24,C10>$B$4*0.8),"Close","No"))
A11: Amazon | B11: =COUNTIFS(Sales!$B:$B,A11,Sales!$A:$A,">="&DATE($B$2,1,1),Sales!$A:$A,"<="&DATE($B$2,12,31)) | C11: =SUMIFS(Sales!$E:$E,Sales!$B:$B,A11,Sales!$A:$A,">="&DATE($B$2,1,1),Sales!$A:$A,"<="&DATE($B$2,12,31)) | D11: =IF(OR(B11>=30,C11>$B$4),"Yes – expect a report",IF(OR(B11>=24,C11>$B$4*0.8),"Close","No"))
A12: Facebook Marketplace | B12: =COUNTIFS(Sales!$B:$B,A12,Sales!$A:$A,">="&DATE($B$2,1,1),Sales!$A:$A,"<="&DATE($B$2,12,31)) | C12: =SUMIFS(Sales!$E:$E,Sales!$B:$B,A12,Sales!$A:$A,">="&DATE($B$2,1,1),Sales!$A:$A,"<="&DATE($B$2,12,31)) | D12: =IF(OR(B12>=30,C12>$B$4),"Yes – expect a report",IF(OR(B12>=24,C12>$B$4*0.8),"Close","No"))
A13: Airbnb | B13: =COUNTIFS(Sales!$B:$B,A13,Sales!$A:$A,">="&DATE($B$2,1,1),Sales!$A:$A,"<="&DATE($B$2,12,31)) | C13: =SUMIFS(Sales!$E:$E,Sales!$B:$B,A13,Sales!$A:$A,">="&DATE($B$2,1,1),Sales!$A:$A,"<="&DATE($B$2,12,31)) | D13: =IF(OR(B13>=30,C13>$B$4),"Yes – expect a report",IF(OR(B13>=24,C13>$B$4*0.8),"Close","No"))
A14: Other | B14: =COUNTIFS(Sales!$B:$B,A14,Sales!$A:$A,">="&DATE($B$2,1,1),Sales!$A:$A,"<="&DATE($B$2,12,31)) | C14: =SUMIFS(Sales!$E:$E,Sales!$B:$B,A14,Sales!$A:$A,">="&DATE($B$2,1,1),Sales!$A:$A,"<="&DATE($B$2,12,31)) | D14: =IF(OR(B14>=30,C14>$B$4),"Yes – expect a report",IF(OR(B14>=24,C14>$B$4*0.8),"Close","No"))
A16: Trading allowance test (tax year)
A17: Gross trading income £ | B17: =SUMIFS(Sales!$E:$E,Sales!$D:$D,"Trading",Sales!$K:$K,$B$3)+SUMIFS(Sales!$F:$F,Sales!$D:$D,"Trading",Sales!$K:$K,$B$3)
A18: Trading profit £ | B18: =SUMIFS(Sales!$J:$J,Sales!$D:$D,"Trading",Sales!$K:$K,$B$3)
A19: What to do | B19: =IF(B17<=1000,"Under £1,000: covered by the trading allowance, nothing to report","Over £1,000: register for Self Assessment; deduct £1,000 OR actual costs, whichever is better")
A21: A record-keeping aid, not tax advice. See gov.uk 'Selling online and paying tax' and 'Tax-free allowances on property and trading income'.

Sheet Sales
A1: Date | B1: Platform | C1: Item | D1: Type | E1: Sale price £ | F1: Postage charged £ | G1: What it cost you £ | H1: Platform fees £ | I1: Postage paid £ | J1: Profit £ | K1: Tax year
J2: =IF(A2="","",N(E2)+N(F2)-N(G2)-N(H2)-N(I2)) | K2: =IF(A2="","",IF(A2>=DATE(YEAR(A2),4,6),YEAR(A2)&"-"&RIGHT(YEAR(A2)+1,2),(YEAR(A2)-1)&"-"&RIGHT(YEAR(A2),2)))
J3: =IF(A3="","",N(E3)+N(F3)-N(G3)-N(H3)-N(I3)) | K3: =IF(A3="","",IF(A3>=DATE(YEAR(A3),4,6),YEAR(A3)&"-"&RIGHT(YEAR(A3)+1,2),(YEAR(A3)-1)&"-"&RIGHT(YEAR(A3),2)))
J4: =IF(A4="","",N(E4)+N(F4)-N(G4)-N(H4)-N(I4)) | K4: =IF(A4="","",IF(A4>=DATE(YEAR(A4),4,6),YEAR(A4)&"-"&RIGHT(YEAR(A4)+1,2),(YEAR(A4)-1)&"-"&RIGHT(YEAR(A4),2)))
J5: =IF(A5="","",N(E5)+N(F5)-N(G5)-N(H5)-N(I5)) | K5: =IF(A5="","",IF(A5>=DATE(YEAR(A5),4,6),YEAR(A5)&"-"&RIGHT(YEAR(A5)+1,2),(YEAR(A5)-1)&"-"&RIGHT(YEAR(A5),2)))
J6: =IF(A6="","",N(E6)+N(F6)-N(G6)-N(H6)-N(I6)) | K6: =IF(A6="","",IF(A6>=DATE(YEAR(A6),4,6),YEAR(A6)&"-"&RIGHT(YEAR(A6)+1,2),(YEAR(A6)-1)&"-"&RIGHT(YEAR(A6),2)))
J7: =IF(A7="","",N(E7)+N(F7)-N(G7)-N(H7)-N(I7)) | K7: =IF(A7="","",IF(A7>=DATE(YEAR(A7),4,6),YEAR(A7)&"-"&RIGHT(YEAR(A7)+1,2),(YEAR(A7)-1)&"-"&RIGHT(YEAR(A7),2)))
J8: =IF(A8="","",N(E8)+N(F8)-N(G8)-N(H8)-N(I8)) | K8: =IF(A8="","",IF(A8>=DATE(YEAR(A8),4,6),YEAR(A8)&"-"&RIGHT(YEAR(A8)+1,2),(YEAR(A8)-1)&"-"&RIGHT(YEAR(A8),2)))
J9: =IF(A9="","",N(E9)+N(F9)-N(G9)-N(H9)-N(I9)) | K9: =IF(A9="","",IF(A9>=DATE(YEAR(A9),4,6),YEAR(A9)&"-"&RIGHT(YEAR(A9)+1,2),(YEAR(A9)-1)&"-"&RIGHT(YEAR(A9),2)))
J10: =IF(A10="","",N(E10)+N(F10)-N(G10)-N(H10)-N(I10)) | K10: =IF(A10="","",IF(A10>=DATE(YEAR(A10),4,6),YEAR(A10)&"-"&RIGHT(YEAR(A10)+1,2),(YEAR(A10)-1)&"-"&RIGHT(YEAR(A10),2)))
J11: =IF(A11="","",N(E11)+N(F11)-N(G11)-N(H11)-N(I11)) | K11: =IF(A11="","",IF(A11>=DATE(YEAR(A11),4,6),YEAR(A11)&"-"&RIGHT(YEAR(A11)+1,2),(YEAR(A11)-1)&"-"&RIGHT(YEAR(A11),2)))
J12: =IF(A12="","",N(E12)+N(F12)-N(G12)-N(H12)-N(I12)) | K12: =IF(A12="","",IF(A12>=DATE(YEAR(A12),4,6),YEAR(A12)&"-"&RIGHT(YEAR(A12)+1,2),(YEAR(A12)-1)&"-"&RIGHT(YEAR(A12),2)))
J13: =IF(A13="","",N(E13)+N(F13)-N(G13)-N(H13)-N(I13)) | K13: =IF(A13="","",IF(A13>=DATE(YEAR(A13),4,6),YEAR(A13)&"-"&RIGHT(YEAR(A13)+1,2),(YEAR(A13)-1)&"-"&RIGHT(YEAR(A13),2)))
... J1001: =IF(A1001="","",N(E1001)+N(F1001)-N(G1001)-N(H1001)-N(I1001)) | K1001: =IF(A1001="","",IF(A1001>=DATE(YEAR(A1001),4,6),YEAR(A1001)&"-"&RIGHT(YEAR(A1001)+1,2),(YEAR(A1001)-1)&"-"&RIGHT(YEAR(A1001),2)))

Sheet Badges of trade
A1: Am I trading? HMRC's 'badges of trade' (answer Yes/No)
A3: Do you buy things with the intention of selling them at a profit?
A4: Do you make things to sell?
A5: Do you sell the same kind of item repeatedly?
A6: Do you change or repair items to sell them for more?
A7: Do you sell in an organised way (stock, listings, a shop name)?
A8: Did you own the items only briefly before selling?
A9: Is selling a regular source of income for you?
A11: Result | B11: =IF(COUNTIF(B3:B9,"Yes")>=2,"Likely trading",IF(COUNTIF(B3:B9,"Yes")=1,"Possibly","Unlikely"))
A12: No single answer decides it. If you're unsure, check gov.uk or ask HMRC. A record-keeping aid, not tax advice. See gov.uk 'Selling online and paying tax' and 'Tax-free allowances on property and trading income'.
