Workbook

Sheet My business
A1: Your details (fill in once – used on every quote and invoice)
A3: Business / trading name
A4: Your name (sole traders must show it)
A5: Address line 1
A6: Address line 2
A7: Town / postcode
A8: Phone
A9: Email
A10: Company number (if limited)
A11: VAT registered? (Yes/No) | B11: No
A12: VAT number
A13: Bank name
A14: Sort code
A15: Account number
A16: Payment terms (days) | B16: 30
A17: Next invoice number | B17: 1001

Sheet Quote
A1: ='My business'!B3 | D1: QUOTE
A2: ='My business'!B4&" · "&'My business'!B5&", "&'My business'!B6&", "&'My business'!B7
A3: ='My business'!B8&" · "&'My business'!B9&IF('My business'!B10<>""," · Company no. "&'My business'!B10,"")
A5: To: | D5: Quote no.
D6: Quote date
D7: Valid until | E7: =IF(E6="","",E6+30)
A11: Description | B11: Qty | C11: Unit price £ | D11: VAT % | E11: Line total £
E12: =IF(B12="","",B12*C12) | F12: =IF(E12="",0,E12*N(D12))
E13: =IF(B13="","",B13*C13) | F13: =IF(E13="",0,E13*N(D13))
E14: =IF(B14="","",B14*C14) | F14: =IF(E14="",0,E14*N(D14))
E15: =IF(B15="","",B15*C15) | F15: =IF(E15="",0,E15*N(D15))
E16: =IF(B16="","",B16*C16) | F16: =IF(E16="",0,E16*N(D16))
E17: =IF(B17="","",B17*C17) | F17: =IF(E17="",0,E17*N(D17))
E18: =IF(B18="","",B18*C18) | F18: =IF(E18="",0,E18*N(D18))
E19: =IF(B19="","",B19*C19) | F19: =IF(E19="",0,E19*N(D19))
E20: =IF(B20="","",B20*C20) | F20: =IF(E20="",0,E20*N(D20))
E21: =IF(B21="","",B21*C21) | F21: =IF(E21="",0,E21*N(D21))
E22: =IF(B22="","",B22*C22) | F22: =IF(E22="",0,E22*N(D22))
E23: =IF(B23="","",B23*C23) | F23: =IF(E23="",0,E23*N(D23))
D25: Subtotal | E25: =SUM(E12:E23)
D26: VAT | E26: =IF('My business'!B11="Yes",SUM(F12:F23),0)
D27: TOTAL | E27: =E25+E26
A29: This quote is a fixed price for the work described. Anything extra will be quoted before it is done.
A30: =IF('My business'!B11="Yes","Prices include VAT where shown. VAT number: "&'My business'!B12,"Not VAT registered – no VAT charged.")

Sheet Invoice
A1: ='My business'!B3 | D1: INVOICE
A2: ='My business'!B4&" · "&'My business'!B5&", "&'My business'!B6&", "&'My business'!B7
A3: ='My business'!B8&" · "&'My business'!B9&IF('My business'!B10<>""," · Company no. "&'My business'!B10,"")
A5: To: | D5: Invoice no. | E5: ='My business'!B17
D6: Invoice date
D7: Tax point / supply date
D8: Due date | E8: =IF(E6="","",E6+'My business'!B16)
A11: Description | B11: Qty | C11: Unit price £ | D11: VAT % | E11: Line total £
E12: =IF(B12="","",B12*C12) | F12: =IF(E12="",0,E12*N(D12))
E13: =IF(B13="","",B13*C13) | F13: =IF(E13="",0,E13*N(D13))
E14: =IF(B14="","",B14*C14) | F14: =IF(E14="",0,E14*N(D14))
E15: =IF(B15="","",B15*C15) | F15: =IF(E15="",0,E15*N(D15))
E16: =IF(B16="","",B16*C16) | F16: =IF(E16="",0,E16*N(D16))
E17: =IF(B17="","",B17*C17) | F17: =IF(E17="",0,E17*N(D17))
E18: =IF(B18="","",B18*C18) | F18: =IF(E18="",0,E18*N(D18))
E19: =IF(B19="","",B19*C19) | F19: =IF(E19="",0,E19*N(D19))
E20: =IF(B20="","",B20*C20) | F20: =IF(E20="",0,E20*N(D20))
E21: =IF(B21="","",B21*C21) | F21: =IF(E21="",0,E21*N(D21))
E22: =IF(B22="","",B22*C22) | F22: =IF(E22="",0,E22*N(D22))
E23: =IF(B23="","",B23*C23) | F23: =IF(E23="",0,E23*N(D23))
D25: Subtotal | E25: =SUM(E12:E23)
D26: VAT | E26: =IF('My business'!B11="Yes",SUM(F12:F23),0)
D27: TOTAL | E27: =E25+E26
A29: ="Please pay to "&'My business'!B13&" · Sort code "&'My business'!B14&" · Account "&'My business'!B15&" · Reference: "&E5
A30: =IF('My business'!B11="Yes","VAT number: "&'My business'!B12,"Not VAT registered – no VAT charged.")

Sheet Invoice log
A1: Invoice no. | B1: Date | C1: Customer | D1: Total £ | E1: Paid on | F1: Days to pay | G1: Status
F2: =IF(OR(B2="",E2=""),"",E2-B2) | G2: =IF(B2="","",IF(E2<>"","Paid",IF(TODAY()-B2>'My business'!$B$16,"OVERDUE","Awaiting")))
F3: =IF(OR(B3="",E3=""),"",E3-B3) | G3: =IF(B3="","",IF(E3<>"","Paid",IF(TODAY()-B3>'My business'!$B$16,"OVERDUE","Awaiting")))
F4: =IF(OR(B4="",E4=""),"",E4-B4) | G4: =IF(B4="","",IF(E4<>"","Paid",IF(TODAY()-B4>'My business'!$B$16,"OVERDUE","Awaiting")))
F5: =IF(OR(B5="",E5=""),"",E5-B5) | G5: =IF(B5="","",IF(E5<>"","Paid",IF(TODAY()-B5>'My business'!$B$16,"OVERDUE","Awaiting")))
F6: =IF(OR(B6="",E6=""),"",E6-B6) | G6: =IF(B6="","",IF(E6<>"","Paid",IF(TODAY()-B6>'My business'!$B$16,"OVERDUE","Awaiting")))
F7: =IF(OR(B7="",E7=""),"",E7-B7) | G7: =IF(B7="","",IF(E7<>"","Paid",IF(TODAY()-B7>'My business'!$B$16,"OVERDUE","Awaiting")))
F8: =IF(OR(B8="",E8=""),"",E8-B8) | G8: =IF(B8="","",IF(E8<>"","Paid",IF(TODAY()-B8>'My business'!$B$16,"OVERDUE","Awaiting")))
F9: =IF(OR(B9="",E9=""),"",E9-B9) | G9: =IF(B9="","",IF(E9<>"","Paid",IF(TODAY()-B9>'My business'!$B$16,"OVERDUE","Awaiting")))
F10: =IF(OR(B10="",E10=""),"",E10-B10) | G10: =IF(B10="","",IF(E10<>"","Paid",IF(TODAY()-B10>'My business'!$B$16,"OVERDUE","Awaiting")))
F11: =IF(OR(B11="",E11=""),"",E11-B11) | G11: =IF(B11="","",IF(E11<>"","Paid",IF(TODAY()-B11>'My business'!$B$16,"OVERDUE","Awaiting")))
F12: =IF(OR(B12="",E12=""),"",E12-B12) | G12: =IF(B12="","",IF(E12<>"","Paid",IF(TODAY()-B12>'My business'!$B$16,"OVERDUE","Awaiting")))
F13: =IF(OR(B13="",E13=""),"",E13-B13) | G13: =IF(B13="","",IF(E13<>"","Paid",IF(TODAY()-B13>'My business'!$B$16,"OVERDUE","Awaiting")))
... F501: =IF(OR(B501="",E501=""),"",E501-B501) | G501: =IF(B501="","",IF(E501<>"","Paid",IF(TODAY()-B501>'My business'!$B$16,"OVERDUE","Awaiting")))

Sheet How to use
A1: 1. Fill in 'My business' once. 2. Copy the Quote or Invoice sheet for each job (right-click tab → Duplicate).
A2: 3. Fill the yellow cells, then File → Print / Save as PDF and send it.
A3: 4. After sending an invoice, add it to 'Invoice log' and raise 'Next invoice number' by 1 – numbers must be unique and in sequence.
A4: Sole traders must show their own name on invoices; limited companies must show the registered company name and number.
A5: Only show VAT if you are VAT registered. VAT invoices must show your VAT number, the tax point and VAT per rate.
A6: Late payment: you can claim statutory interest and compensation on overdue business-to-business invoices (gov.uk/late-commercial-payments-interest-debt-recovery).
A7: A template to help you invoice correctly – not legal or tax advice.
